praetorian_api_client/__init__.py
praetorian_api_client/api_client.py
praetorian_api_client/configuration.py
praetorian_api_client/errors.py
praetorian_api_client/requestor.py
praetorian_api_client/resources/__init__.py
praetorian_api_client/resources/base.py
praetorian_api_client/resources/log.py
praetorian_api_client/resources/project.py
praetorian_api_client/resources/remote.py
praetorian_api_client/resources/service.py
praetorian_api_client/resources/token.py
praetorian_api_client/resources/user.py
praetorian_api_client/utils.py
praetorian_api_client/version.py
praetorian_api_client-0.5.0.dist-info/LICENSE
praetorian_api_client-0.5.0.dist-info/METADATA
praetorian_api_client-0.5.0.dist-info/WHEEL
praetorian_api_client-0.5.0.dist-info/RECORD
