Metadata-Version: 2.1
Name: praetorian-api-client
Version: 0.5.0
Summary: API Client for praetorian-api project.
License: MIT
Author: Adam Žúrek
Author-email: adamzurek14@gmail.com
Requires-Python: >=3.9,<4.0
Classifier: License :: OSI Approved :: MIT License
Classifier: Programming Language :: Python :: 3
Classifier: Programming Language :: Python :: 3.9
Classifier: Programming Language :: Python :: 3.10
Classifier: Programming Language :: Python :: 3.11
Classifier: Programming Language :: Python :: 3.12
Requires-Dist: python-dotenv (>=0.15.0,<0.16.0)
Requires-Dist: requests (>=2.31.0,<3.0.0)
Project-URL: Changelog, https://github.com/Praetorian-Defence/praetorian-api-client/blob/main/CHANGELOG.md
Project-URL: Issues, https://github.com/Praetorian-Defence/praetorian-api-client/issues
Project-URL: Repository, https://github.com/Praetorian-Defence/praetorian-api-client
